[
  {
    "id": "zero-percent-down-financing",
    "title": "0% Down Financing",
    "description": "Flexible financing with nothing down to get your project started",
    "order": 1
  },
  {
    "id": "free-estimates",
    "title": "Free Estimates",
    "description": "No-cost, no-obligation estimates on every project",
    "order": 2
  },
  {
    "id": "licensed-and-insured",
    "title": "Licensed & Insured",
    "description": "Fully licensed and insured for your peace of mind",
    "order": 3
  },
  {
    "id": "roofing-and-decks",
    "title": "Roofing & Decks",
    "description": "Expert roof replacement and custom deck construction",
    "order": 4
  },
  {
    "id": "lifetime-warranty",
    "title": "Lifetime Warranty Available",
    "description": "Long-lasting protection backed by lifetime warranty options",
    "order": 5
  },
  {
    "id": "locally-owned",
    "title": "Locally Owned & Operated",
    "description": "A local team you can count on, right in your community",
    "order": 6
  }
]
